mds_jl6276_finalproject/__init__.py
mds_jl6276_finalproject/config.py
mds_jl6276_finalproject/mds_jl6276_finalproject.py
mds_jl6276_finalproject-0.1.0.dist-info/LICENSE
mds_jl6276_finalproject-0.1.0.dist-info/WHEEL
mds_jl6276_finalproject-0.1.0.dist-info/METADATA
mds_jl6276_finalproject-0.1.0.dist-info/RECORD
