Metadata-Version: 2.1
Name: mds-jl6276-finalproject
Version: 0.1.0
Summary: A final project for MDS 2022 Fall. It includes a function that relies on Yelp api, and the funtion takes in a catagory in terms like 'bars', 'restaurant', etc... and return the location of resaurant in New York On map.
License: MIT
Author: Jin Liu
Requires-Python: >=3.9,<4.0
Classifier: License :: OSI Approved :: MIT License
Classifier: Programming Language :: Python :: 3
Classifier: Programming Language :: Python :: 3.9
Classifier: Programming Language :: Python :: 3.10
Classifier: Programming Language :: Python :: 3.11
Requires-Dist: folium (>=0.14.0,<0.15.0)
Requires-Dist: pandas (>=1.5.2,<2.0.0)
